odoo/addons/base_repair_config/README.rst
odoo/addons/base_repair_config/__init__.py
odoo/addons/base_repair_config/__manifest__.py
odoo/addons/base_repair_config/i18n/base_repair_config.pot
odoo/addons/base_repair_config/i18n/ca.po
odoo/addons/base_repair_config/i18n/es.po
odoo/addons/base_repair_config/i18n/it.po
odoo/addons/base_repair_config/i18n/pt_BR.po
odoo/addons/base_repair_config/readme/CONFIGURE.md
odoo/addons/base_repair_config/readme/CONTRIBUTORS.md
odoo/addons/base_repair_config/readme/DESCRIPTION.md
odoo/addons/base_repair_config/readme/USAGE.md
odoo/addons/base_repair_config/static/description/banner.png
odoo/addons/base_repair_config/static/description/icon.png
odoo/addons/base_repair_config/static/description/index.html
odoo/addons/base_repair_config/views/res_config_settings.xml
odoo_addon_base_repair_config-18.0.1.0.0.2.dist-info/METADATA
odoo_addon_base_repair_config-18.0.1.0.0.2.dist-info/WHEEL
odoo_addon_base_repair_config-18.0.1.0.0.2.dist-info/top_level.txt
odoo_addon_base_repair_config-18.0.1.0.0.2.dist-info/RECORD
